[
  {
    "Action": [
      "dynamodb:Query",
      "dynamodb:Scan",
      "dynamodb:GetItem",
      "dynamodb:UpdateItem"
    ],
    "Resource": [
      "arn:aws:dynamodb:ap-southeast-2:*:table/ScraperJob-*",
      "arn:aws:dynamodb:ap-southeast-2:*:table/ScraperJob-*/index/*"
    ]
  },
  {
    "Action": [
      "dynamodb:Scan",
      "dynamodb:GetItem",
      "dynamodb:UpdateItem"
    ],
    "Resource": [
      "arn:aws:dynamodb:ap-southeast-2:*:table/ScrapeURL-*"
    ]
  },
  {
    "Action": [
      "dynamodb:Scan"
    ],
    "Resource": [
      "arn:aws:dynamodb:ap-southeast-2:*:table/ScrapeAttempt-*"
    ]
  },
  {
    "Action": [
      "dynamodb:GetItem",
      "dynamodb:UpdateItem"
    ],
    "Resource": [
      "arn:aws:dynamodb:ap-southeast-2:*:table/ScraperState-*"
    ]
  },
  {
    "Action": [
      "lambda:InvokeFunction"
    ],
    "Resource": [
      "arn:aws:lambda:ap-southeast-2:*:function:autoScraper-*"
    ]
  },
  {
    "Action": [
      "cloudwatch:PutMetricData"
    ],
    "Resource": [
      "*"
    ]
  }
]